README.md
setup.py
glemmazon/__init__.py
glemmazon/cleanup.py
glemmazon/constants.py
glemmazon/encoder.py
glemmazon/extract_exceptions.py
glemmazon/pipeline.py
glemmazon/preprocess.py
glemmazon/train_analyzer.py
glemmazon/train_inflector.py
glemmazon/train_lemmatizer.py
glemmazon/utils.py
glemmazon.egg-info/PKG-INFO
glemmazon.egg-info/SOURCES.txt
glemmazon.egg-info/dependency_links.txt
glemmazon.egg-info/not-zip-safe
glemmazon.egg-info/requires.txt
glemmazon.egg-info/top_level.txt